{
  "date": "2026-07-02",
  "generatedAt": "2026-07-01T20:30:02.561Z",
  "ga4": {
    "range": "7daysAgo..yesterday",
    "sessions": 212,
    "users": 196,
    "views": 295,
    "avgDurationSec": 80,
    "taiwanOrganicSessions": 171,
    "channels": [
      {
        "channel": "Organic Search",
        "sessions": 176
      },
      {
        "channel": "Unassigned",
        "sessions": 20
      },
      {
        "channel": "Direct",
        "sessions": 18
      },
      {
        "channel": "Cross-network",
        "sessions": 13
      },
      {
        "channel": "Referral",
        "sessions": 2
      }
    ],
    "topPages": [
      {
        "path": "/",
        "views": 19
      },
      {
        "path": "/poems/",
        "views": 5
      },
      {
        "path": "/deities/xuantian/",
        "views": 4
      },
      {
        "path": "/temples/",
        "views": 4
      },
      {
        "path": "/temples/region/taitung/鹿野鄉/",
        "views": 4
      },
      {
        "path": "/allusions/jiangzhongli/",
        "views": 3
      },
      {
        "path": "/deities/guanyin/",
        "views": 3
      },
      {
        "path": "/deities/wangye/",
        "views": 3
      },
      {
        "path": "/deities/wangye_chi/",
        "views": 3
      },
      {
        "path": "/poems/liushi_jiazi-46/",
        "views": 3
      },
      {
        "path": "/poems/liushi_jiazi-47/",
        "views": 3
      },
      {
        "path": "/temples/moi_172_震威宮/",
        "views": 3
      },
      {
        "path": "/temples/moi_2695_財團法人高雄市鼓/",
        "views": 3
      },
      {
        "path": "/temples/moi_671_天威慈惠堂/",
        "views": 3
      },
      {
        "path": "/temples/region/pingtung/九如鄉/",
        "views": 3
      }
    ]
  },
  "gsc": {
    "range": "2026-06-22..2026-06-29",
    "totals": {
      "clicks": 172,
      "impressions": 9845,
      "ctr": 0.017470797359065517,
      "position": 10.802133062468258
    },
    "topQueries": [
      {
        "query": "吳孝寬",
        "clicks": 2,
        "impressions": 38,
        "ctr": 0.05263157894736842,
        "position": 6.605263157894737
      },
      {
        "query": "普照業寺",
        "clicks": 2,
        "impressions": 22,
        "ctr": 0.09090909090909091,
        "position": 6.363636363636363
      },
      {
        "query": "江中立欽賜狀元",
        "clicks": 2,
        "impressions": 6,
        "ctr": 0.3333333333333333,
        "position": 7
      },
      {
        "query": "辛巳籤",
        "clicks": 2,
        "impressions": 2,
        "ctr": 1,
        "position": 42
      },
      {
        "query": "一重江水一重山 誰知此去路又難 任他改求終不過 是非終久未得安",
        "clicks": 1,
        "impressions": 1,
        "ctr": 1,
        "position": 16
      },
      {
        "query": "仁德興安宮",
        "clicks": 1,
        "impressions": 3,
        "ctr": 0.3333333333333333,
        "position": 8.666666666666668
      },
      {
        "query": "保仁宮",
        "clicks": 1,
        "impressions": 8,
        "ctr": 0.125,
        "position": 7.75
      },
      {
        "query": "凶事脫出化成吉",
        "clicks": 1,
        "impressions": 1,
        "ctr": 1,
        "position": 58
      },
      {
        "query": "劉厝聖帝宮",
        "clicks": 1,
        "impressions": 2,
        "ctr": 0.5,
        "position": 21.5
      },
      {
        "query": "劉小姐愛蒙正 解籤",
        "clicks": 1,
        "impressions": 1,
        "ctr": 1,
        "position": 22
      },
      {
        "query": "南中慈惠堂",
        "clicks": 1,
        "impressions": 1,
        "ctr": 1,
        "position": 10
      },
      {
        "query": "南巡殿",
        "clicks": 1,
        "impressions": 5,
        "ctr": 0.2,
        "position": 7
      },
      {
        "query": "南港慈雲寺",
        "clicks": 1,
        "impressions": 4,
        "ctr": 0.25,
        "position": 9.75
      },
      {
        "query": "古恩宮",
        "clicks": 1,
        "impressions": 9,
        "ctr": 0.1111111111111111,
        "position": 11.11111111111111
      },
      {
        "query": "台南慈雲宮",
        "clicks": 1,
        "impressions": 156,
        "ctr": 0.00641025641025641,
        "position": 7.544871794871795
      },
      {
        "query": "嘯聚山林兇惡儔姻緣",
        "clicks": 1,
        "impressions": 1,
        "ctr": 1,
        "position": 46
      },
      {
        "query": "壬午籤感情",
        "clicks": 1,
        "impressions": 3,
        "ctr": 0.3333333333333333,
        "position": 11.666666666666666
      },
      {
        "query": "壬寅籤感情",
        "clicks": 1,
        "impressions": 1,
        "ctr": 1,
        "position": 21
      },
      {
        "query": "大宅中安宮",
        "clicks": 1,
        "impressions": 5,
        "ctr": 0.2,
        "position": 5
      },
      {
        "query": "大無極聖殿",
        "clicks": 1,
        "impressions": 7,
        "ctr": 0.14285714285714285,
        "position": 10.571428571428571
      },
      {
        "query": "大玄廟",
        "clicks": 1,
        "impressions": 8,
        "ctr": 0.125,
        "position": 10.75
      },
      {
        "query": "峰月宮",
        "clicks": 1,
        "impressions": 1,
        "ctr": 1,
        "position": 11
      },
      {
        "query": "彰化慈惠堂",
        "clicks": 1,
        "impressions": 1,
        "ctr": 1,
        "position": 12
      },
      {
        "query": "戊辰籤",
        "clicks": 1,
        "impressions": 2,
        "ctr": 0.5,
        "position": 20
      },
      {
        "query": "東勢泰安宮",
        "clicks": 1,
        "impressions": 1,
        "ctr": 1,
        "position": 13
      }
    ],
    "topPages": [
      {
        "page": "https://folk.tw/poems/liushi_jiazi-45/",
        "clicks": 4,
        "impressions": 16,
        "ctr": 0.25,
        "position": 26.1875
      },
      {
        "page": "https://folk.tw/allusions/tonggin_zhixue/",
        "clicks": 3,
        "impressions": 11,
        "ctr": 0.2727272727272727,
        "position": 8.454545454545453
      },
      {
        "page": "https://folk.tw/deities/wangye_wu/",
        "clicks": 3,
        "impressions": 61,
        "ctr": 0.04918032786885246,
        "position": 8.278688524590164
      },
      {
        "page": "https://folk.tw/allusions/jiangzhongli/",
        "clicks": 2,
        "impressions": 10,
        "ctr": 0.2,
        "position": 6.2
      },
      {
        "page": "https://folk.tw/allusions/suitang_qinshubao/",
        "clicks": 2,
        "impressions": 31,
        "ctr": 0.06451612903225806,
        "position": 7.064516129032258
      },
      {
        "page": "https://folk.tw/poems/guandi_lingqian-5/",
        "clicks": 2,
        "impressions": 8,
        "ctr": 0.25,
        "position": 8.5
      },
      {
        "page": "https://folk.tw/poems/guandi_lingqian-61/",
        "clicks": 2,
        "impressions": 11,
        "ctr": 0.18181818181818182,
        "position": 12.727272727272727
      },
      {
        "page": "https://folk.tw/poems/liushi_jiazi-27/",
        "clicks": 2,
        "impressions": 9,
        "ctr": 0.2222222222222222,
        "position": 31.444444444444443
      },
      {
        "page": "https://folk.tw/poems/liushi_jiazi-47/",
        "clicks": 2,
        "impressions": 14,
        "ctr": 0.14285714285714285,
        "position": 44
      },
      {
        "page": "https://folk.tw/temples/moi_12003_%E6%99%AE%E7%85%A7%E6%A5%AD%E5%AF%BA/",
        "clicks": 2,
        "impressions": 42,
        "ctr": 0.047619047619047616,
        "position": 6.738095238095238
      },
      {
        "page": "https://folk.tw/temples/moi_2695_%E8%B2%A1%E5%9C%98%E6%B3%95%E4%BA%BA%E9%AB%98%E9%9B%84%E5%B8%82%E9%BC%93/",
        "clicks": 2,
        "impressions": 4,
        "ctr": 0.5,
        "position": 8.25
      },
      {
        "page": "https://folk.tw/temples/moi_2772_%E5%BB%A3%E9%BE%8D%E7%A6%AA%E5%AF%BA/",
        "clicks": 2,
        "impressions": 8,
        "ctr": 0.25,
        "position": 9.375
      },
      {
        "page": "https://folk.tw/temples/moi_7038_%E5%8C%97%E9%9A%86%E5%AE%AE/",
        "clicks": 2,
        "impressions": 12,
        "ctr": 0.16666666666666666,
        "position": 6
      },
      {
        "page": "https://folk.tw/temples/region/nantou/%E4%B8%AD%E5%AF%AE%E9%84%89/",
        "clicks": 2,
        "impressions": 26,
        "ctr": 0.07692307692307693,
        "position": 7.576923076923077
      },
      {
        "page": "https://folk.tw/temples/region/pingtung/%E6%96%B0%E5%9C%92%E9%84%89",
        "clicks": 2,
        "impressions": 6,
        "ctr": 0.3333333333333333,
        "position": 6.666666666666667
      },
      {
        "page": "https://folk.tw/temples/region/taitung/%E6%88%90%E5%8A%9F%E9%8E%AE/",
        "clicks": 2,
        "impressions": 6,
        "ctr": 0.3333333333333333,
        "position": 11.666666666666666
      },
      {
        "page": "https://folk.tw/allusions/gd_14/",
        "clicks": 1,
        "impressions": 5,
        "ctr": 0.2,
        "position": 5.2
      },
      {
        "page": "https://folk.tw/allusions/gd_24/",
        "clicks": 1,
        "impressions": 8,
        "ctr": 0.125,
        "position": 9.875
      },
      {
        "page": "https://folk.tw/allusions/gd_31/",
        "clicks": 1,
        "impressions": 1,
        "ctr": 1,
        "position": 14
      },
      {
        "page": "https://folk.tw/allusions/gd_75/",
        "clicks": 1,
        "impressions": 5,
        "ctr": 0.2,
        "position": 9.4
      },
      {
        "page": "https://folk.tw/allusions/gd_92/",
        "clicks": 1,
        "impressions": 1,
        "ctr": 1,
        "position": 9
      },
      {
        "page": "https://folk.tw/allusions/suqin/",
        "clicks": 1,
        "impressions": 7,
        "ctr": 0.14285714285714285,
        "position": 8.428571428571429
      },
      {
        "page": "https://folk.tw/allusions/zhengde_lifeng/",
        "clicks": 1,
        "impressions": 3,
        "ctr": 0.3333333333333333,
        "position": 8.333333333333332
      },
      {
        "page": "https://folk.tw/almanac/2027-03-22/",
        "clicks": 1,
        "impressions": 1,
        "ctr": 1,
        "position": 9
      },
      {
        "page": "https://folk.tw/deities/dasheng/",
        "clicks": 1,
        "impressions": 7,
        "ctr": 0.14285714285714285,
        "position": 5.857142857142857
      }
    ],
    "pageQueryCross": [
      {
        "page": "https://folk.tw/allusions/jiangzhongli/",
        "query": "江中立欽賜狀元",
        "clicks": 2,
        "impressions": 6,
        "ctr": 0.3333333333333333,
        "position": 7
      },
      {
        "page": "https://folk.tw/deities/wangye_wu/",
        "query": "吳孝寬",
        "clicks": 2,
        "impressions": 38,
        "ctr": 0.05263157894736842,
        "position": 6.605263157894737
      },
      {
        "page": "https://folk.tw/poems/liushi_jiazi-45/",
        "query": "辛巳籤",
        "clicks": 2,
        "impressions": 2,
        "ctr": 1,
        "position": 42
      },
      {
        "page": "https://folk.tw/temples/moi_12003_%E6%99%AE%E7%85%A7%E6%A5%AD%E5%AF%BA/",
        "query": "普照業寺",
        "clicks": 2,
        "impressions": 22,
        "ctr": 0.09090909090909091,
        "position": 6.363636363636363
      },
      {
        "page": "https://folk.tw/allusions/suitang_qinshubao/",
        "query": "楊管醉玉仝坐馬",
        "clicks": 1,
        "impressions": 13,
        "ctr": 0.07692307692307693,
        "position": 7
      },
      {
        "page": "https://folk.tw/allusions/suitang_qinshubao/",
        "query": "楊管醉玉仝坐馬故事",
        "clicks": 1,
        "impressions": 4,
        "ctr": 0.25,
        "position": 6
      },
      {
        "page": "https://folk.tw/allusions/tonggin_zhixue/",
        "query": "銅銀買紙靴",
        "clicks": 1,
        "impressions": 4,
        "ctr": 0.25,
        "position": 6.25
      },
      {
        "page": "https://folk.tw/allusions/zhengde_lifeng/",
        "query": "正德君戲李鳳姐",
        "clicks": 1,
        "impressions": 2,
        "ctr": 0.5,
        "position": 8
      },
      {
        "page": "https://folk.tw/deities/wangye_fan/",
        "query": "范府千歲",
        "clicks": 1,
        "impressions": 2,
        "ctr": 0.5,
        "position": 22.5
      },
      {
        "page": "https://folk.tw/poems/guandi_lingqian-1/",
        "query": "漢高祖入關解籤",
        "clicks": 1,
        "impressions": 1,
        "ctr": 1,
        "position": 14
      },
      {
        "page": "https://folk.tw/poems/guandi_lingqian-43/",
        "query": "玄德公黃鶴樓赴宴",
        "clicks": 1,
        "impressions": 5,
        "ctr": 0.2,
        "position": 5.6
      },
      {
        "page": "https://folk.tw/poems/guandi_lingqian-61/",
        "query": "嘯聚山林兇惡儔姻緣",
        "clicks": 1,
        "impressions": 1,
        "ctr": 1,
        "position": 46
      },
      {
        "page": "https://folk.tw/poems/guandi_lingqian-73/",
        "query": "王昭君憶漢帝",
        "clicks": 1,
        "impressions": 1,
        "ctr": 1,
        "position": 13
      },
      {
        "page": "https://folk.tw/poems/guandi_lingqian-75/",
        "query": "劉小姐愛蒙正 解籤",
        "clicks": 1,
        "impressions": 1,
        "ctr": 1,
        "position": 22
      },
      {
        "page": "https://folk.tw/poems/liushi_jiazi-27/",
        "query": "戊辰籤",
        "clicks": 1,
        "impressions": 2,
        "ctr": 0.5,
        "position": 20
      },
      {
        "page": "https://folk.tw/poems/liushi_jiazi-40/",
        "query": "第40籤",
        "clicks": 1,
        "impressions": 1,
        "ctr": 1,
        "position": 48
      },
      {
        "page": "https://folk.tw/poems/liushi_jiazi-42/",
        "query": "一重江水一重山 誰知此去路又難 任他改求終不過 是非終久未得安",
        "clicks": 1,
        "impressions": 1,
        "ctr": 1,
        "position": 16
      },
      {
        "page": "https://folk.tw/poems/liushi_jiazi-46/",
        "query": "辛未籤感情",
        "clicks": 1,
        "impressions": 1,
        "ctr": 1,
        "position": 33
      },
      {
        "page": "https://folk.tw/poems/liushi_jiazi-47/",
        "query": "凶事脫出化成吉",
        "clicks": 1,
        "impressions": 1,
        "ctr": 1,
        "position": 58
      },
      {
        "page": "https://folk.tw/poems/liushi_jiazi-47/",
        "query": "第四十七籤運勢",
        "clicks": 1,
        "impressions": 1,
        "ctr": 1,
        "position": 85
      },
      {
        "page": "https://folk.tw/poems/liushi_jiazi-50/",
        "query": "壬寅籤感情",
        "clicks": 1,
        "impressions": 1,
        "ctr": 1,
        "position": 21
      },
      {
        "page": "https://folk.tw/poems/liushi_jiazi-52/",
        "query": "壬午籤感情",
        "clicks": 1,
        "impressions": 3,
        "ctr": 0.3333333333333333,
        "position": 11.666666666666666
      },
      {
        "page": "https://folk.tw/poems/liushi_jiazi-56/",
        "query": "楊戩得病在西軒",
        "clicks": 1,
        "impressions": 1,
        "ctr": 1,
        "position": 37
      },
      {
        "page": "https://folk.tw/temples/moi_10951_%E5%A4%A7%E5%AE%85%E4%B8%AD%E5%AE%89%E5%AE%AE/",
        "query": "大宅中安宮",
        "clicks": 1,
        "impressions": 5,
        "ctr": 0.2,
        "position": 5
      },
      {
        "page": "https://folk.tw/temples/moi_11157_%E5%A4%A7%E7%8E%84%E5%BB%9F/",
        "query": "大玄廟",
        "clicks": 1,
        "impressions": 8,
        "ctr": 0.125,
        "position": 10.75
      },
      {
        "page": "https://folk.tw/temples/moi_11830_%E5%8F%B0%E5%8C%97%E4%BF%9D%E4%BB%81%E5%AE%AE/",
        "query": "保仁宮",
        "clicks": 1,
        "impressions": 8,
        "ctr": 0.125,
        "position": 7.75
      },
      {
        "page": "https://folk.tw/temples/moi_11914_%E8%B2%A1%E5%9C%98%E6%B3%95%E4%BA%BA%E5%BD%B0%E5%8C%96%E7%B8%A3%E8%AD%A6/",
        "query": "警化堂",
        "clicks": 1,
        "impressions": 6,
        "ctr": 0.16666666666666666,
        "position": 9.666666666666666
      },
      {
        "page": "https://folk.tw/temples/moi_12116_%E5%8D%97%E5%B7%A1%E6%AE%BF/",
        "query": "南巡殿",
        "clicks": 1,
        "impressions": 5,
        "ctr": 0.2,
        "position": 7
      },
      {
        "page": "https://folk.tw/temples/moi_12136_%E5%A4%AA%E5%85%83%E5%AE%AE/",
        "query": "社頭太元宮",
        "clicks": 1,
        "impressions": 132,
        "ctr": 0.007575757575757576,
        "position": 9.537878787878787
      },
      {
        "page": "https://folk.tw/temples/moi_2146_%E6%85%88%E9%9B%B2%E5%AE%AE/",
        "query": "台南慈雲宮",
        "clicks": 1,
        "impressions": 50,
        "ctr": 0.02,
        "position": 7.68
      },
      {
        "page": "https://folk.tw/temples/moi_2313_%E4%BB%81%E5%BE%B7%E8%88%88%E5%AE%89%E5%AE%AE/",
        "query": "仁德興安宮",
        "clicks": 1,
        "impressions": 3,
        "ctr": 0.3333333333333333,
        "position": 8.666666666666668
      },
      {
        "page": "https://folk.tw/temples/moi_3142_%E9%A6%AC%E5%85%89%E5%8D%97%E5%A4%A9%E5%AE%AE/",
        "query": "馬光南天宮",
        "clicks": 1,
        "impressions": 3,
        "ctr": 0.3333333333333333,
        "position": 6.666666666666667
      },
      {
        "page": "https://folk.tw/temples/moi_3279_%E7%A2%A7%E9%9B%B2%E5%AE%AE/",
        "query": "深澳碧雲宮",
        "clicks": 1,
        "impressions": 1,
        "ctr": 1,
        "position": 13
      },
      {
        "page": "https://folk.tw/temples/moi_3796_%E8%A7%80%E9%9F%B3%E4%BD%9B%E7%A5%96%E5%BB%9F/",
        "query": "溝心觀音佛祖廟",
        "clicks": 1,
        "impressions": 2,
        "ctr": 0.5,
        "position": 14.5
      },
      {
        "page": "https://folk.tw/temples/moi_5135_%E6%B3%B0%E5%AE%89%E5%AE%AE/",
        "query": "東勢泰安宮",
        "clicks": 1,
        "impressions": 1,
        "ctr": 1,
        "position": 13
      },
      {
        "page": "https://folk.tw/temples/moi_5638_%E8%81%96%E5%B8%9D%E5%AE%AE/",
        "query": "劉厝聖帝宮",
        "clicks": 1,
        "impressions": 2,
        "ctr": 0.5,
        "position": 21.5
      },
      {
        "page": "https://folk.tw/temples/moi_5934_%E5%B3%B0%E6%9C%88%E5%AE%AE/",
        "query": "峰月宮",
        "clicks": 1,
        "impressions": 1,
        "ctr": 1,
        "position": 11
      },
      {
        "page": "https://folk.tw/temples/moi_6895_%E5%8D%97%E4%B8%AD%E6%85%88%E6%83%A0%E5%A0%82/",
        "query": "南中慈惠堂",
        "clicks": 1,
        "impressions": 1,
        "ctr": 1,
        "position": 10
      },
      {
        "page": "https://folk.tw/temples/moi_699_%E5%8F%A4%E6%81%A9%E5%AE%AE/",
        "query": "古恩宮",
        "clicks": 1,
        "impressions": 9,
        "ctr": 0.1111111111111111,
        "position": 11.11111111111111
      },
      {
        "page": "https://folk.tw/temples/moi_7083_%E5%8D%97%E6%B8%AF%E6%85%88%E9%9B%B2%E5%AF%BA/",
        "query": "南港慈雲寺",
        "clicks": 1,
        "impressions": 4,
        "ctr": 0.25,
        "position": 9.75
      },
      {
        "page": "https://folk.tw/temples/moi_7989_%E4%B8%89%E5%85%83%E5%AE%AE/",
        "query": "車埕三元宮",
        "clicks": 1,
        "impressions": 16,
        "ctr": 0.0625,
        "position": 10
      },
      {
        "page": "https://folk.tw/temples/moi_8140_%E8%81%96%E5%92%8C%E5%AE%AE/",
        "query": "聖和宮籤詩",
        "clicks": 1,
        "impressions": 9,
        "ctr": 0.1111111111111111,
        "position": 6.444444444444445
      },
      {
        "page": "https://folk.tw/temples/moi_81_%E8%8A%B1%E8%93%AE%E9%96%8B%E9%9D%88%E5%AE%AE/",
        "query": "花蓮開靈宮",
        "clicks": 1,
        "impressions": 1,
        "ctr": 1,
        "position": 25
      },
      {
        "page": "https://folk.tw/temples/moi_9418_%E5%A4%A7%E7%84%A1%E6%A5%B5%E8%81%96%E6%AE%BF/",
        "query": "大無極聖殿",
        "clicks": 1,
        "impressions": 7,
        "ctr": 0.14285714285714285,
        "position": 10.571428571428571
      },
      {
        "page": "https://folk.tw/temples/moi_9517_%E5%BD%B0%E5%8C%96%E6%85%88%E6%83%A0%E5%A0%82/",
        "query": "彰化慈惠堂",
        "clicks": 1,
        "impressions": 1,
        "ctr": 1,
        "position": 12
      },
      {
        "page": "https://folk.tw/temples/region/pingtung/%E6%BD%AE%E5%B7%9E%E9%8E%AE",
        "query": "潮州慈龍宮",
        "clicks": 1,
        "impressions": 33,
        "ctr": 0.030303030303030304,
        "position": 10.909090909090908
      },
      {
        "page": "https://folk.tw/allusions/gd_14/",
        "query": "郭華戀王月英",
        "clicks": 0,
        "impressions": 2,
        "ctr": 0,
        "position": 5
      },
      {
        "page": "https://folk.tw/allusions/gd_24/",
        "query": "張騫誤入斗牛宮",
        "clicks": 0,
        "impressions": 1,
        "ctr": 0,
        "position": 27
      },
      {
        "page": "https://folk.tw/allusions/gd_27/",
        "query": "江東得道",
        "clicks": 0,
        "impressions": 3,
        "ctr": 0,
        "position": 10.333333333333334
      },
      {
        "page": "https://folk.tw/allusions/gd_32/",
        "query": "周公之夢",
        "clicks": 0,
        "impressions": 1,
        "ctr": 0,
        "position": 10
      },
      {
        "page": "https://folk.tw/allusions/gd_35/",
        "query": "昭君",
        "clicks": 0,
        "impressions": 2,
        "ctr": 0,
        "position": 49.5
      },
      {
        "page": "https://folk.tw/allusions/gd_35/",
        "query": "王昭君",
        "clicks": 0,
        "impressions": 1,
        "ctr": 0,
        "position": 91
      },
      {
        "page": "https://folk.tw/allusions/gd_45",
        "query": "丁公",
        "clicks": 0,
        "impressions": 2,
        "ctr": 0,
        "position": 11
      },
      {
        "page": "https://folk.tw/allusions/gd_45",
        "query": "丁公 劉邦",
        "clicks": 0,
        "impressions": 1,
        "ctr": 0,
        "position": 12
      },
      {
        "page": "https://folk.tw/allusions/gd_51/",
        "query": "御溝流紅葉",
        "clicks": 0,
        "impressions": 2,
        "ctr": 0,
        "position": 3.5
      },
      {
        "page": "https://folk.tw/allusions/gd_66/",
        "query": "杜甫遊春",
        "clicks": 0,
        "impressions": 2,
        "ctr": 0,
        "position": 9
      },
      {
        "page": "https://folk.tw/allusions/gd_72/",
        "query": "范蠡",
        "clicks": 0,
        "impressions": 1,
        "ctr": 0,
        "position": 48
      },
      {
        "page": "https://folk.tw/allusions/gd_95/",
        "query": "張文遠",
        "clicks": 0,
        "impressions": 1,
        "ctr": 0,
        "position": 11
      },
      {
        "page": "https://folk.tw/allusions/kongzi_xiaoer/",
        "query": "孔夫子與小兒答",
        "clicks": 0,
        "impressions": 1,
        "ctr": 0,
        "position": 20
      },
      {
        "page": "https://folk.tw/allusions/soushen",
        "query": "范丹洗浴遇賢妻",
        "clicks": 0,
        "impressions": 9,
        "ctr": 0,
        "position": 10
      },
      {
        "page": "https://folk.tw/allusions/suitang_qinshubao/",
        "query": "秦叔寶救李淵",
        "clicks": 0,
        "impressions": 9,
        "ctr": 0,
        "position": 8.88888888888889
      },
      {
        "page": "https://folk.tw/allusions/suqin/",
        "query": "蘇秦假不第",
        "clicks": 0,
        "impressions": 1,
        "ctr": 0,
        "position": 8
      },
      {
        "page": "https://folk.tw/allusions/suqin/",
        "query": "蘇秦回家假不第",
        "clicks": 0,
        "impressions": 1,
        "ctr": 0,
        "position": 22
      },
      {
        "page": "https://folk.tw/allusions/suqin/",
        "query": "蘇秦回家假不第故事",
        "clicks": 0,
        "impressions": 2,
        "ctr": 0,
        "position": 6.5
      },
      {
        "page": "https://folk.tw/allusions/wuhan_qizhu/",
        "query": "吳漢殺妻救母救主",
        "clicks": 0,
        "impressions": 1,
        "ctr": 0,
        "position": 7
      },
      {
        "page": "https://folk.tw/allusions/wuhan_qizhu/",
        "query": "吳漢殺妻為母救主",
        "clicks": 0,
        "impressions": 16,
        "ctr": 0,
        "position": 8.625
      },
      {
        "page": "https://folk.tw/allusions/yangjiajiang/",
        "query": "楊文廣被困柳州城",
        "clicks": 0,
        "impressions": 2,
        "ctr": 0,
        "position": 11
      },
      {
        "page": "https://folk.tw/allusions/yangjiajiang/",
        "query": "楊文廣被困柳州城故事",
        "clicks": 0,
        "impressions": 4,
        "ctr": 0,
        "position": 7
      },
      {
        "page": "https://folk.tw/almanac",
        "query": "拜拜 日子",
        "clicks": 0,
        "impressions": 1,
        "ctr": 0,
        "position": 88
      },
      {
        "page": "https://folk.tw/almanac/2025-06-13/",
        "query": "2025/06/13",
        "clicks": 0,
        "impressions": 1,
        "ctr": 0,
        "position": 6
      },
      {
        "page": "https://folk.tw/almanac/2025-08-29/",
        "query": "2025-08-29",
        "clicks": 0,
        "impressions": 3,
        "ctr": 0,
        "position": 8.666666666666668
      },
      {
        "page": "https://folk.tw/almanac/2025-09-09/",
        "query": "2025-09-09",
        "clicks": 0,
        "impressions": 1,
        "ctr": 0,
        "position": 8
      },
      {
        "page": "https://folk.tw/almanac/2025-10-02/",
        "query": "2025/10/02",
        "clicks": 0,
        "impressions": 1,
        "ctr": 0,
        "position": 7
      },
      {
        "page": "https://folk.tw/almanac/2026-02-01/",
        "query": "2026/02/01",
        "clicks": 0,
        "impressions": 1,
        "ctr": 0,
        "position": 10
      },
      {
        "page": "https://folk.tw/almanac/2026-05-07/",
        "query": "2026/05/07",
        "clicks": 0,
        "impressions": 1,
        "ctr": 0,
        "position": 6
      },
      {
        "page": "https://folk.tw/almanac/2026-07-08/",
        "query": "2026/07/08",
        "clicks": 0,
        "impressions": 1,
        "ctr": 0,
        "position": 9
      },
      {
        "page": "https://folk.tw/almanac/2026-08-15",
        "query": "農曆 八 月 十 五",
        "clicks": 0,
        "impressions": 1,
        "ctr": 0,
        "position": 59
      },
      {
        "page": "https://folk.tw/almanac/2026-12-08/",
        "query": "12-08-2026",
        "clicks": 0,
        "impressions": 1,
        "ctr": 0,
        "position": 2
      },
      {
        "page": "https://folk.tw/deities/baosheng/",
        "query": "保生 大帝",
        "clicks": 0,
        "impressions": 1,
        "ctr": 0,
        "position": 75
      },
      {
        "page": "https://folk.tw/deities/chenghuang/",
        "query": "城隍",
        "clicks": 0,
        "impressions": 3,
        "ctr": 0,
        "position": 68.66666666666667
      },
      {
        "page": "https://folk.tw/deities/chenghuang/",
        "query": "城隍 爺",
        "clicks": 0,
        "impressions": 3,
        "ctr": 0,
        "position": 56
      },
      {
        "page": "https://folk.tw/deities/chenghuang/",
        "query": "城隍是誰",
        "clicks": 0,
        "impressions": 2,
        "ctr": 0,
        "position": 71.5
      },
      {
        "page": "https://folk.tw/deities/chenghuang/",
        "query": "城隍神 とは",
        "clicks": 0,
        "impressions": 1,
        "ctr": 0,
        "position": 78
      },
      {
        "page": "https://folk.tw/deities/dasheng",
        "query": "大聖爺",
        "clicks": 0,
        "impressions": 15,
        "ctr": 0,
        "position": 11.866666666666667
      },
      {
        "page": "https://folk.tw/deities/dongyue/",
        "query": "東 嶽 大帝",
        "clicks": 0,
        "impressions": 1,
        "ctr": 0,
        "position": 73
      },
      {
        "page": "https://folk.tw/deities/dongyue/",
        "query": "東獄廟",
        "clicks": 0,
        "impressions": 1,
        "ctr": 0,
        "position": 1
      },
      {
        "page": "https://folk.tw/deities/fazhu/",
        "query": "法 主公",
        "clicks": 0,
        "impressions": 2,
        "ctr": 0,
        "position": 44
      },
      {
        "page": "https://folk.tw/deities/fazhu/",
        "query": "法 祖 公",
        "clicks": 0,
        "impressions": 3,
        "ctr": 0,
        "position": 51.333333333333336
      },
      {
        "page": "https://folk.tw/deities/fazhu/",
        "query": "法主公",
        "clicks": 0,
        "impressions": 1,
        "ctr": 0,
        "position": 53
      },
      {
        "page": "https://folk.tw/deities/guangze/",
        "query": "廣澤 尊王",
        "clicks": 0,
        "impressions": 1,
        "ctr": 0,
        "position": 41
      },
      {
        "page": "https://folk.tw/deities/guangze/",
        "query": "廣澤尊王",
        "clicks": 0,
        "impressions": 2,
        "ctr": 0,
        "position": 77
      },
      {
        "page": "https://folk.tw/deities/guanping/",
        "query": "關平太子封號",
        "clicks": 0,
        "impressions": 2,
        "ctr": 0,
        "position": 12
      },
      {
        "page": "https://folk.tw/deities/guanyin/",
        "query": "觀世音",
        "clicks": 0,
        "impressions": 1,
        "ctr": 0,
        "position": 66
      },
      {
        "page": "https://folk.tw/deities/guanyin/",
        "query": "觀世音 菩薩",
        "clicks": 0,
        "impressions": 4,
        "ctr": 0,
        "position": 62.75
      },
      {
        "page": "https://folk.tw/deities/guanyin/",
        "query": "觀世音菩薩",
        "clicks": 0,
        "impressions": 2,
        "ctr": 0,
        "position": 55
      },
      {
        "page": "https://folk.tw/deities/guanyin/",
        "query": "觀音",
        "clicks": 0,
        "impressions": 1,
        "ctr": 0,
        "position": 80
      },
      {
        "page": "https://folk.tw/deities/guanyin/",
        "query": "觀音 佛祖",
        "clicks": 0,
        "impressions": 1,
        "ctr": 0,
        "position": 76
      },
      {
        "page": "https://folk.tw/deities/guanyin/",
        "query": "觀音 菩薩",
        "clicks": 0,
        "impressions": 1,
        "ctr": 0,
        "position": 77
      },
      {
        "page": "https://folk.tw/deities/guanyin/",
        "query": "觀音是誰",
        "clicks": 0,
        "impressions": 1,
        "ctr": 0,
        "position": 74
      },
      {
        "page": "https://folk.tw/deities/guanyin/",
        "query": "觀音菩薩",
        "clicks": 0,
        "impressions": 1,
        "ctr": 0,
        "position": 47
      },
      {
        "page": "https://folk.tw/deities/huagong/",
        "query": "花公花婆意思",
        "clicks": 0,
        "impressions": 2,
        "ctr": 0,
        "position": 8.5
      },
      {
        "page": "https://folk.tw/deities/huye/",
        "query": "虎 爺",
        "clicks": 0,
        "impressions": 2,
        "ctr": 0,
        "position": 79
      },
      {
        "page": "https://folk.tw/deities/jiutian",
        "query": "九天 玄 女",
        "clicks": 0,
        "impressions": 1,
        "ctr": 0,
        "position": 46
      },
      {
        "page": "https://folk.tw/deities/jiutian/",
        "query": "南化靈山九天宮",
        "clicks": 0,
        "impressions": 1,
        "ctr": 0,
        "position": 11
      },
      {
        "page": "https://folk.tw/deities/jiutian/",
        "query": "玄天上帝九天玄女關係",
        "clicks": 0,
        "impressions": 1,
        "ctr": 0,
        "position": 20
      },
      {
        "page": "https://folk.tw/deities/kaizhang/",
        "query": "開 漳 聖王",
        "clicks": 0,
        "impressions": 3,
        "ctr": 0,
        "position": 60
      },
      {
        "page": "https://folk.tw/deities/kuixing/",
        "query": "魁斗星君",
        "clicks": 0,
        "impressions": 1,
        "ctr": 0,
        "position": 99
      },
      {
        "page": "https://folk.tw/deities/leigongdianmu/",
        "query": "雷公神明",
        "clicks": 0,
        "impressions": 1,
        "ctr": 0,
        "position": 14
      },
      {
        "page": "https://folk.tw/deities/miaoying_xianfei/",
        "query": "妙應仙妃由來",
        "clicks": 0,
        "impressions": 5,
        "ctr": 0,
        "position": 11.2
      },
      {
        "page": "https://folk.tw/deities/miaoying_xianfei/",
        "query": "妙應仙妃管什麼",
        "clicks": 0,
        "impressions": 1,
        "ctr": 0,
        "position": 6
      },
      {
        "page": "https://folk.tw/deities/miaoying_xianfei/",
        "query": "廣澤尊王夫人",
        "clicks": 0,
        "impressions": 1,
        "ctr": 0,
        "position": 11
      },
      {
        "page": "https://folk.tw/deities/nazha/",
        "query": "中 坛 元帅",
        "clicks": 0,
        "impressions": 1,
        "ctr": 0,
        "position": 55
      },
      {
        "page": "https://folk.tw/deities/nazha/",
        "query": "中 壇 元帥",
        "clicks": 0,
        "impressions": 1,
        "ctr": 0,
        "position": 60
      },
      {
        "page": "https://folk.tw/deities/qiyebaye/",
        "query": "七 爺",
        "clicks": 0,
        "impressions": 1,
        "ctr": 0,
        "position": 41
      },
      {
        "page": "https://folk.tw/deities/qiyebaye/",
        "query": "七爺",
        "clicks": 0,
        "impressions": 1,
        "ctr": 0,
        "position": 40
      },
      {
        "page": "https://folk.tw/deities/qiyebaye/",
        "query": "七爺八爺",
        "clicks": 0,
        "impressions": 1,
        "ctr": 0,
        "position": 39
      },
      {
        "page": "https://folk.tw/deities/qiyebaye/",
        "query": "七爺八爺生日",
        "clicks": 0,
        "impressions": 3,
        "ctr": 0,
        "position": 10
      },
      {
        "page": "https://folk.tw/deities/qiyebaye/",
        "query": "七爺八爺聖誕",
        "clicks": 0,
        "impressions": 26,
        "ctr": 0,
        "position": 7.538461538461538
      },
      {
        "page": "https://folk.tw/deities/qiyebaye/",
        "query": "七爺生日",
        "clicks": 0,
        "impressions": 3,
        "ctr": 0,
        "position": 8.333333333333332
      },
      {
        "page": "https://folk.tw/deities/qiyebaye/",
        "query": "七爺謝將軍",
        "clicks": 0,
        "impressions": 1,
        "ctr": 0,
        "position": 8
      },
      {
        "page": "https://folk.tw/deities/qiyebaye/",
        "query": "八爺聖誕",
        "clicks": 0,
        "impressions": 5,
        "ctr": 0,
        "position": 9.4
      },
      {
        "page": "https://folk.tw/deities/qiyebaye/",
        "query": "范將軍生日",
        "clicks": 0,
        "impressions": 7,
        "ctr": 0,
        "position": 11.285714285714286
      },
      {
        "page": "https://folk.tw/deities/qiyebaye/",
        "query": "謝將軍生日",
        "clicks": 0,
        "impressions": 1,
        "ctr": 0,
        "position": 8
      },
      {
        "page": "https://folk.tw/deities/qiyebaye/",
        "query": "謝范將軍聖誕",
        "clicks": 0,
        "impressions": 7,
        "ctr": 0,
        "position": 9.857142857142858
      },
      {
        "page": "https://folk.tw/deities/shennong/",
        "query": "神農",
        "clicks": 0,
        "impressions": 1,
        "ctr": 0,
        "position": 55
      },
      {
        "page": "https://folk.tw/deities/shennong/",
        "query": "神農 大帝",
        "clicks": 0,
        "impressions": 1,
        "ctr": 0,
        "position": 76
      },
      {
        "page": "https://folk.tw/deities/tiandu",
        "query": "田 都 元帥",
        "clicks": 0,
        "impressions": 1,
        "ctr": 0,
        "position": 46
      },
      {
        "page": "https://folk.tw/deities/tudigong",
        "query": "福 德 正 神",
        "clicks": 0,
        "impressions": 1,
        "ctr": 0,
        "position": 58
      },
      {
        "page": "https://folk.tw/deities/wangye_chi/",
        "query": "池 府 千歲",
        "clicks": 0,
        "impressions": 1,
        "ctr": 0,
        "position": 51
      },
      {
        "page": "https://folk.tw/deities/wangye_chi/",
        "query": "池府千歲",
        "clicks": 0,
        "impressions": 1,
        "ctr": 0,
        "position": 50
      },
      {
        "page": "https://folk.tw/deities/wangye_chi/",
        "query": "池府千歲封號",
        "clicks": 0,
        "impressions": 1,
        "ctr": 0,
        "position": 11
      },
      {
        "page": "https://folk.tw/deities/wangye_fan",
        "query": "范府",
        "clicks": 0,
        "impressions": 9,
        "ctr": 0,
        "position": 9.88888888888889
      },
      {
        "page": "https://folk.tw/deities/wangye_fan",
        "query": "范府千歲",
        "clicks": 0,
        "impressions": 1,
        "ctr": 0,
        "position": 20
      },
      {
        "page": "https://folk.tw/deities/wangye_fan",
        "query": "范府千歲由來",
        "clicks": 0,
        "impressions": 4,
        "ctr": 0,
        "position": 10.5
      },
      {
        "page": "https://folk.tw/deities/wangye_fan",
        "query": "范承業",
        "clicks": 0,
        "impressions": 10,
        "ctr": 0,
        "position": 9.9
      },
      {
        "page": "https://folk.tw/deities/wangye_fan/",
        "query": "范府",
        "clicks": 0,
        "impressions": 1,
        "ctr": 0,
        "position": 12
      },
      {
        "page": "https://folk.tw/deities/wangye_fan/",
        "query": "范承業",
        "clicks": 0,
        "impressions": 13,
        "ctr": 0,
        "position": 9.615384615384615
      },
      {
        "page": "https://folk.tw/deities/wangye_li/",
        "query": "李 府 王爺",
        "clicks": 0,
        "impressions": 1,
        "ctr": 0,
        "position": 67
      },
      {
        "page": "https://folk.tw/deities/wangye_li/",
        "query": "李大王",
        "clicks": 0,
        "impressions": 2,
        "ctr": 0,
        "position": 11
      },
      {
        "page": "https://folk.tw/deities/wangye_li/",
        "query": "李府千歲",
        "clicks": 0,
        "impressions": 1,
        "ctr": 0,
        "position": 50
      },
      {
        "page": "https://folk.tw/deities/wangye_wu/",
        "query": "吳 府 千歲",
        "clicks": 0,
        "impressions": 1,
        "ctr": 0,
        "position": 48
      },
      {
        "page": "https://folk.tw/deities/wangye_wu/",
        "query": "吳府千歲幾歲",
        "clicks": 0,
        "impressions": 10,
        "ctr": 0,
        "position": 7.6
      },
      {
        "page": "https://folk.tw/deities/wangye_zhu/",
        "query": "朱叔裕",
        "clicks": 0,
        "impressions": 10,
        "ctr": 0,
        "position": 9.2
      },
      {
        "page": "https://folk.tw/deities/yuelao",
        "query": "月下老人",
        "clicks": 0,
        "impressions": 1,
        "ctr": 0,
        "position": 92
      },
      {
        "page": "https://folk.tw/deities/yuelao/",
        "query": "月 下 老人",
        "clicks": 0,
        "impressions": 2,
        "ctr": 0,
        "position": 59.5
      },
      {
        "page": "https://folk.tw/deities/yuhuang",
        "query": "玉皇",
        "clicks": 0,
        "impressions": 1,
        "ctr": 0,
        "position": 69
      },
      {
        "page": "https://folk.tw/deities/yuhuang/",
        "query": "玉皇大帝",
        "clicks": 0,
        "impressions": 2,
        "ctr": 0,
        "position": 58
      },
      {
        "page": "https://folk.tw/deities/zhuyi_shenjun/",
        "query": "朱衣神君",
        "clicks": 0,
        "impressions": 1,
        "ctr": 0,
        "position": 30
      },
      {
        "page": "https://folk.tw/events/beigang/",
        "query": "北港",
        "clicks": 0,
        "impressions": 1,
        "ctr": 0,
        "position": 36
      },
      {
        "page": "https://folk.tw/poems/guandi_lingqian-1/",
        "query": "漢高祖入關",
        "clicks": 0,
        "impressions": 5,
        "ctr": 0,
        "position": 6.8
      },
      {
        "page": "https://folk.tw/poems/guandi_lingqian-15/",
        "query": "張君瑞憶鶯鶯",
        "clicks": 0,
        "impressions": 1,
        "ctr": 0,
        "position": 14
      },
      {
        "page": "https://folk.tw/poems/guandi_lingqian-16/",
        "query": "王祥臥冰解籤",
        "clicks": 0,
        "impressions": 1,
        "ctr": 0,
        "position": 14
      },
      {
        "page": "https://folk.tw/poems/guandi_lingqian-18/",
        "query": "知君指擬是空華 底事茫茫未有涯 牢把腳根踏實地 善為善應永無差",
        "clicks": 0,
        "impressions": 1,
        "ctr": 0,
        "position": 1
      },
      {
        "page": "https://folk.tw/poems/guandi_lingqian-19/",
        "query": "劉智遠得岳氏",
        "clicks": 0,
        "impressions": 5,
        "ctr": 0,
        "position": 9
      },
      {
        "page": "https://folk.tw/poems/guandi_lingqian-24/",
        "query": "張騫誤入斗牛宮",
        "clicks": 0,
        "impressions": 4,
        "ctr": 0,
        "position": 12.5
      },
      {
        "page": "https://folk.tw/poems/guandi_lingqian-34/",
        "query": "蕭何追韓信",
        "clicks": 0,
        "impressions": 1,
        "ctr": 0,
        "position": 4
      },
      {
        "page": "https://folk.tw/poems/guandi_lingqian-35",
        "query": "一山如畫對清江運勢",
        "clicks": 0,
        "impressions": 1,
        "ctr": 0,
        "position": 52
      },
      {
        "page": "https://folk.tw/poems/guandi_lingqian-43/",
        "query": "玄德宮黃鶴樓赴宴 感情",
        "clicks": 0,
        "impressions": 1,
        "ctr": 0,
        "position": 5
      },
      {
        "page": "https://folk.tw/poems/guandi_lingqian-51/",
        "query": "御溝流紅葉",
        "clicks": 0,
        "impressions": 1,
        "ctr": 0,
        "position": 12
      },
      {
        "page": "https://folk.tw/poems/guandi_lingqian-59/",
        "query": "鄧伯道無兒",
        "clicks": 0,
        "impressions": 1,
        "ctr": 0,
        "position": 26
      },
      {
        "page": "https://folk.tw/poems/guandi_lingqian-63/",
        "query": "楊令公撞李陵碑",
        "clicks": 0,
        "impressions": 3,
        "ctr": 0,
        "position": 8
      },
      {
        "page": "https://folk.tw/poems/guandi_lingqian-70/",
        "query": "王曾祈禱",
        "clicks": 0,
        "impressions": 1,
        "ctr": 0,
        "position": 8
      },
      {
        "page": "https://folk.tw/poems/guandi_lingqian-70/",
        "query": "雷雨風雲各有司至誠禱告莫生疑與君定約為霖日正是蘊隆中伏時工作",
        "clicks": 0,
        "impressions": 1,
        "ctr": 0,
        "position": 54
      },
      {
        "page": "https://folk.tw/poems/guandi_lingqian-72/",
        "query": "河渠傍路有高低 可歎長途日已西 縱有榮華好時節 直須猴犬換金雞",
        "clicks": 0,
        "impressions": 1,
        "ctr": 0,
        "position": 48
      },
      {
        "page": "https://folk.tw/poems/guandi_lingqian-76/",
        "query": "關聖帝君76籤",
        "clicks": 0,
        "impressions": 1,
        "ctr": 0,
        "position": 20
      },
      {
        "page": "https://folk.tw/poems/guandi_lingqian-81/",
        "query": "寇公任雷陽",
        "clicks": 0,
        "impressions": 1,
        "ctr": 0,
        "position": 29
      },
      {
        "page": "https://folk.tw/poems/guandi_lingqian-96/",
        "query": "山濤見王衍",
        "clicks": 0,
        "impressions": 1,
        "ctr": 0,
        "position": 25
      },
      {
        "page": "https://folk.tw/poems/liushi_jiazi-10/",
        "query": "第10籤乙未",
        "clicks": 0,
        "impressions": 1,
        "ctr": 0,
        "position": 27
      },
      {
        "page": "https://folk.tw/poems/liushi_jiazi-11/",
        "query": "第11籤",
        "clicks": 0,
        "impressions": 1,
        "ctr": 0,
        "position": 76
      },
      {
        "page": "https://folk.tw/poems/liushi_jiazi-11/",
        "query": "靈雞漸漸見分明感情發展",
        "clicks": 0,
        "impressions": 1,
        "ctr": 0,
        "position": 79
      },
      {
        "page": "https://folk.tw/poems/liushi_jiazi-11/",
        "query": "韓文公過秦嶺湘子掃霜雪",
        "clicks": 0,
        "impressions": 1,
        "ctr": 0,
        "position": 31
      },
      {
        "page": "https://folk.tw/poems/liushi_jiazi-13/",
        "query": "丙子籤",
        "clicks": 0,
        "impressions": 1,
        "ctr": 0,
        "position": 62
      },
      {
        "page": "https://folk.tw/poems/liushi_jiazi-17/",
        "query": "丙申籤",
        "clicks": 0,
        "impressions": 3,
        "ctr": 0,
        "position": 18.666666666666668
      },
      {
        "page": "https://folk.tw/poems/liushi_jiazi-18",
        "query": "君問中間此言因 看看祿馬拱前程 求得貴人多得利 和合自有兩分明",
        "clicks": 0,
        "impressions": 1,
        "ctr": 0,
        "position": 18
      },
      {
        "page": "https://folk.tw/poems/liushi_jiazi-18/",
        "query": "楊管醉玉仝坐馬",
        "clicks": 0,
        "impressions": 2,
        "ctr": 0,
        "position": 12.5
      },
      {
        "page": "https://folk.tw/poems/liushi_jiazi-2/",
        "query": "于今此景正當時 看看欲吐百花魁 若能遇得春色到 一洒清吉脫塵埃",
        "clicks": 0,
        "impressions": 1,
        "ctr": 0,
        "position": 24
      },
      {
        "page": "https://folk.tw/poems/liushi_jiazi-2/",
        "query": "于今此景正當時，看看欲吐百花魁 若能遇得春色到，一洒清吉脫塵埃。",
        "clicks": 0,
        "impressions": 2,
        "ctr": 0,
        "position": 24.5
      },
      {
        "page": "https://folk.tw/poems/liushi_jiazi-2/",
        "query": "于今此景正當時，看看欲吐百花魁若能遇得春色到，一洒清吉脫塵埃。",
        "clicks": 0,
        "impressions": 1,
        "ctr": 0,
        "position": 42
      },
      {
        "page": "https://folk.tw/poems/liushi_jiazi-2/",
        "query": "於今此景正當時 看看欲吐百花魁 若能遇得春色到 一洒清吉脫塵埃。",
        "clicks": 0,
        "impressions": 1,
        "ctr": 0,
        "position": 33
      },
      {
        "page": "https://folk.tw/poems/liushi_jiazi-2/",
        "query": "看看欲吐百花魁",
        "clicks": 0,
        "impressions": 2,
        "ctr": 0,
        "position": 10
      },
      {
        "page": "https://folk.tw/poems/liushi_jiazi-20/",
        "query": "勸君且退莫咨嗟",
        "clicks": 0,
        "impressions": 1,
        "ctr": 0,
        "position": 17
      },
      {
        "page": "https://folk.tw/poems/liushi_jiazi-23/",
        "query": "丁酉籤",
        "clicks": 0,
        "impressions": 1,
        "ctr": 0,
        "position": 18
      },
      {
        "page": "https://folk.tw/poems/liushi_jiazi-23/",
        "query": "如今絲綸常在手",
        "clicks": 0,
        "impressions": 2,
        "ctr": 0,
        "position": 15
      },
      {
        "page": "https://folk.tw/poems/liushi_jiazi-23/",
        "query": "欲去長江水闊茫 前途未遂運未通 如今絲綸常在手 只恐魚水不相逢 工作",
        "clicks": 0,
        "impressions": 1,
        "ctr": 0,
        "position": 37
      },
      {
        "page": "https://folk.tw/poems/liushi_jiazi-23/",
        "query": "欲去長江水闊茫，前途未遂運未通 如今絲綸常在手，只恐魚水不相逢。",
        "clicks": 0,
        "impressions": 1,
        "ctr": 0,
        "position": 28
      },
      {
        "page": "https://folk.tw/poems/liushi_jiazi-25/",
        "query": "總是前途莫心勞，求神問聖枉是多 但看雞犬日過後，不須作福事如何。",
        "clicks": 0,
        "impressions": 3,
        "ctr": 0,
        "position": 23
      },
      {
        "page": "https://folk.tw/poems/liushi_jiazi-25/",
        "query": "總是前途莫心勞，求神問聖枉是多但看雞犬日過後，不須作福事如何。",
        "clicks": 0,
        "impressions": 1,
        "ctr": 0,
        "position": 45
      },
      {
        "page": "https://folk.tw/poems/liushi_jiazi-26/",
        "query": "戊寅籤",
        "clicks": 0,
        "impressions": 1,
        "ctr": 0,
        "position": 29
      },
      {
        "page": "https://folk.tw/poems/liushi_jiazi-26/",
        "query": "戊寅籤感情",
        "clicks": 0,
        "impressions": 1,
        "ctr": 0,
        "position": 72
      },
      {
        "page": "https://folk.tw/poems/liushi_jiazi-27/",
        "query": "27籤",
        "clicks": 0,
        "impressions": 1,
        "ctr": 0,
        "position": 34
      },
      {
        "page": "https://folk.tw/poems/liushi_jiazi-27/",
        "query": "君爾寬心且自由",
        "clicks": 0,
        "impressions": 1,
        "ctr": 0,
        "position": 65
      },
      {
        "page": "https://folk.tw/poems/liushi_jiazi-29",
        "query": "枯木可惜逢春時",
        "clicks": 0,
        "impressions": 1,
        "ctr": 0,
        "position": 40
      },
      {
        "page": "https://folk.tw/poems/liushi_jiazi-29",
        "query": "枯木可惜逢春時，如今還在暗中藏 寬心且守風霜退，還君依舊作乾坤。",
        "clicks": 0,
        "impressions": 1,
        "ctr": 0,
        "position": 37
      },
      {
        "page": "https://folk.tw/poems/liushi_jiazi-33/",
        "query": "己巳籤",
        "clicks": 0,
        "impressions": 2,
        "ctr": 0,
        "position": 27.5
      },
      {
        "page": "https://folk.tw/poems/liushi_jiazi-35/",
        "query": "此事何須用心機 前途變怪自然知 看看此去得和合 漸漸脫出見太平",
        "clicks": 0,
        "impressions": 1,
        "ctr": 0,
        "position": 16
      },
      {
        "page": "https://folk.tw/poems/liushi_jiazi-35/",
        "query": "此事何須用心機，前途變怪自然知 看看此去得和合，漸漸脫出見太平。",
        "clicks": 0,
        "impressions": 1,
        "ctr": 0,
        "position": 16
      },
      {
        "page": "https://folk.tw/poems/liushi_jiazi-35/",
        "query": "此事何須用心機，前途變怪自然知看看此去得和合，漸漸脫出見太平。",
        "clicks": 0,
        "impressions": 1,
        "ctr": 0,
        "position": 16
      },
      {
        "page": "https://folk.tw/poems/liushi_jiazi-36/",
        "query": "己亥籤",
        "clicks": 0,
        "impressions": 1,
        "ctr": 0,
        "position": 54
      },
      {
        "page": "https://folk.tw/poems/liushi_jiazi-36/",
        "query": "福如東海壽如山 君爾何須嘆苦難 命內自然逢大吉 祈保分明得平安",
        "clicks": 0,
        "impressions": 1,
        "ctr": 0,
        "position": 20
      },
      {
        "page": "https://folk.tw/poems/liushi_jiazi-36/",
        "query": "福如東海壽如山 君爾何須嘆苦難 命內自然逢大吉 祈保分明得平安。",
        "clicks": 0,
        "impressions": 1,
        "ctr": 0,
        "position": 20
      }
    ],
    "strikingDistance": [
      {
        "page": "https://folk.tw/temples/moi_12136_%E5%A4%AA%E5%85%83%E5%AE%AE/",
        "query": "社頭太元宮",
        "clicks": 1,
        "impressions": 132,
        "ctr": 0.007575757575757576,
        "position": 9.537878787878787
      },
      {
        "page": "https://folk.tw/temples/moi_2146_%E6%85%88%E9%9B%B2%E5%AE%AE/",
        "query": "台南慈雲宮",
        "clicks": 1,
        "impressions": 50,
        "ctr": 0.02,
        "position": 7.68
      },
      {
        "page": "https://folk.tw/deities/wangye_wu/",
        "query": "吳孝寬",
        "clicks": 2,
        "impressions": 38,
        "ctr": 0.05263157894736842,
        "position": 6.605263157894737
      },
      {
        "page": "https://folk.tw/temples/region/pingtung/%E6%BD%AE%E5%B7%9E%E9%8E%AE",
        "query": "潮州慈龍宮",
        "clicks": 1,
        "impressions": 33,
        "ctr": 0.030303030303030304,
        "position": 10.909090909090908
      },
      {
        "page": "https://folk.tw/deities/qiyebaye/",
        "query": "七爺八爺聖誕",
        "clicks": 0,
        "impressions": 26,
        "ctr": 0,
        "position": 7.538461538461538
      },
      {
        "page": "https://folk.tw/temples/moi_12003_%E6%99%AE%E7%85%A7%E6%A5%AD%E5%AF%BA/",
        "query": "普照業寺",
        "clicks": 2,
        "impressions": 22,
        "ctr": 0.09090909090909091,
        "position": 6.363636363636363
      },
      {
        "page": "https://folk.tw/temples/moi_7989_%E4%B8%89%E5%85%83%E5%AE%AE/",
        "query": "車埕三元宮",
        "clicks": 1,
        "impressions": 16,
        "ctr": 0.0625,
        "position": 10
      },
      {
        "page": "https://folk.tw/allusions/wuhan_qizhu/",
        "query": "吳漢殺妻為母救主",
        "clicks": 0,
        "impressions": 16,
        "ctr": 0,
        "position": 8.625
      },
      {
        "page": "https://folk.tw/deities/dasheng",
        "query": "大聖爺",
        "clicks": 0,
        "impressions": 15,
        "ctr": 0,
        "position": 11.866666666666667
      },
      {
        "page": "https://folk.tw/allusions/suitang_qinshubao/",
        "query": "楊管醉玉仝坐馬",
        "clicks": 1,
        "impressions": 13,
        "ctr": 0.07692307692307693,
        "position": 7
      },
      {
        "page": "https://folk.tw/deities/wangye_fan/",
        "query": "范承業",
        "clicks": 0,
        "impressions": 13,
        "ctr": 0,
        "position": 9.615384615384615
      },
      {
        "page": "https://folk.tw/deities/wangye_fan",
        "query": "范承業",
        "clicks": 0,
        "impressions": 10,
        "ctr": 0,
        "position": 9.9
      },
      {
        "page": "https://folk.tw/deities/wangye_wu/",
        "query": "吳府千歲幾歲",
        "clicks": 0,
        "impressions": 10,
        "ctr": 0,
        "position": 7.6
      },
      {
        "page": "https://folk.tw/deities/wangye_zhu/",
        "query": "朱叔裕",
        "clicks": 0,
        "impressions": 10,
        "ctr": 0,
        "position": 9.2
      },
      {
        "page": "https://folk.tw/temples/moi_699_%E5%8F%A4%E6%81%A9%E5%AE%AE/",
        "query": "古恩宮",
        "clicks": 1,
        "impressions": 9,
        "ctr": 0.1111111111111111,
        "position": 11.11111111111111
      },
      {
        "page": "https://folk.tw/temples/moi_8140_%E8%81%96%E5%92%8C%E5%AE%AE/",
        "query": "聖和宮籤詩",
        "clicks": 1,
        "impressions": 9,
        "ctr": 0.1111111111111111,
        "position": 6.444444444444445
      },
      {
        "page": "https://folk.tw/allusions/soushen",
        "query": "范丹洗浴遇賢妻",
        "clicks": 0,
        "impressions": 9,
        "ctr": 0,
        "position": 10
      },
      {
        "page": "https://folk.tw/allusions/suitang_qinshubao/",
        "query": "秦叔寶救李淵",
        "clicks": 0,
        "impressions": 9,
        "ctr": 0,
        "position": 8.88888888888889
      },
      {
        "page": "https://folk.tw/deities/wangye_fan",
        "query": "范府",
        "clicks": 0,
        "impressions": 9,
        "ctr": 0,
        "position": 9.88888888888889
      },
      {
        "page": "https://folk.tw/temples/moi_11157_%E5%A4%A7%E7%8E%84%E5%BB%9F/",
        "query": "大玄廟",
        "clicks": 1,
        "impressions": 8,
        "ctr": 0.125,
        "position": 10.75
      },
      {
        "page": "https://folk.tw/temples/moi_11830_%E5%8F%B0%E5%8C%97%E4%BF%9D%E4%BB%81%E5%AE%AE/",
        "query": "保仁宮",
        "clicks": 1,
        "impressions": 8,
        "ctr": 0.125,
        "position": 7.75
      },
      {
        "page": "https://folk.tw/temples/moi_9418_%E5%A4%A7%E7%84%A1%E6%A5%B5%E8%81%96%E6%AE%BF/",
        "query": "大無極聖殿",
        "clicks": 1,
        "impressions": 7,
        "ctr": 0.14285714285714285,
        "position": 10.571428571428571
      },
      {
        "page": "https://folk.tw/deities/qiyebaye/",
        "query": "范將軍生日",
        "clicks": 0,
        "impressions": 7,
        "ctr": 0,
        "position": 11.285714285714286
      },
      {
        "page": "https://folk.tw/deities/qiyebaye/",
        "query": "謝范將軍聖誕",
        "clicks": 0,
        "impressions": 7,
        "ctr": 0,
        "position": 9.857142857142858
      },
      {
        "page": "https://folk.tw/allusions/jiangzhongli/",
        "query": "江中立欽賜狀元",
        "clicks": 2,
        "impressions": 6,
        "ctr": 0.3333333333333333,
        "position": 7
      },
      {
        "page": "https://folk.tw/temples/moi_11914_%E8%B2%A1%E5%9C%98%E6%B3%95%E4%BA%BA%E5%BD%B0%E5%8C%96%E7%B8%A3%E8%AD%A6/",
        "query": "警化堂",
        "clicks": 1,
        "impressions": 6,
        "ctr": 0.16666666666666666,
        "position": 9.666666666666666
      },
      {
        "page": "https://folk.tw/poems/guandi_lingqian-43/",
        "query": "玄德公黃鶴樓赴宴",
        "clicks": 1,
        "impressions": 5,
        "ctr": 0.2,
        "position": 5.6
      },
      {
        "page": "https://folk.tw/temples/moi_10951_%E5%A4%A7%E5%AE%85%E4%B8%AD%E5%AE%89%E5%AE%AE/",
        "query": "大宅中安宮",
        "clicks": 1,
        "impressions": 5,
        "ctr": 0.2,
        "position": 5
      },
      {
        "page": "https://folk.tw/temples/moi_12116_%E5%8D%97%E5%B7%A1%E6%AE%BF/",
        "query": "南巡殿",
        "clicks": 1,
        "impressions": 5,
        "ctr": 0.2,
        "position": 7
      },
      {
        "page": "https://folk.tw/deities/miaoying_xianfei/",
        "query": "妙應仙妃由來",
        "clicks": 0,
        "impressions": 5,
        "ctr": 0,
        "position": 11.2
      }
    ],
    "highImpZeroClick": [
      {
        "page": "https://folk.tw/deities/qiyebaye/",
        "query": "七爺八爺聖誕",
        "clicks": 0,
        "impressions": 26,
        "ctr": 0,
        "position": 7.538461538461538
      },
      {
        "page": "https://folk.tw/allusions/wuhan_qizhu/",
        "query": "吳漢殺妻為母救主",
        "clicks": 0,
        "impressions": 16,
        "ctr": 0,
        "position": 8.625
      },
      {
        "page": "https://folk.tw/deities/dasheng",
        "query": "大聖爺",
        "clicks": 0,
        "impressions": 15,
        "ctr": 0,
        "position": 11.866666666666667
      },
      {
        "page": "https://folk.tw/deities/wangye_fan/",
        "query": "范承業",
        "clicks": 0,
        "impressions": 13,
        "ctr": 0,
        "position": 9.615384615384615
      },
      {
        "page": "https://folk.tw/deities/wangye_fan",
        "query": "范承業",
        "clicks": 0,
        "impressions": 10,
        "ctr": 0,
        "position": 9.9
      },
      {
        "page": "https://folk.tw/deities/wangye_wu/",
        "query": "吳府千歲幾歲",
        "clicks": 0,
        "impressions": 10,
        "ctr": 0,
        "position": 7.6
      },
      {
        "page": "https://folk.tw/deities/wangye_zhu/",
        "query": "朱叔裕",
        "clicks": 0,
        "impressions": 10,
        "ctr": 0,
        "position": 9.2
      },
      {
        "page": "https://folk.tw/allusions/soushen",
        "query": "范丹洗浴遇賢妻",
        "clicks": 0,
        "impressions": 9,
        "ctr": 0,
        "position": 10
      },
      {
        "page": "https://folk.tw/allusions/suitang_qinshubao/",
        "query": "秦叔寶救李淵",
        "clicks": 0,
        "impressions": 9,
        "ctr": 0,
        "position": 8.88888888888889
      },
      {
        "page": "https://folk.tw/deities/wangye_fan",
        "query": "范府",
        "clicks": 0,
        "impressions": 9,
        "ctr": 0,
        "position": 9.88888888888889
      },
      {
        "page": "https://folk.tw/deities/qiyebaye/",
        "query": "范將軍生日",
        "clicks": 0,
        "impressions": 7,
        "ctr": 0,
        "position": 11.285714285714286
      },
      {
        "page": "https://folk.tw/deities/qiyebaye/",
        "query": "謝范將軍聖誕",
        "clicks": 0,
        "impressions": 7,
        "ctr": 0,
        "position": 9.857142857142858
      },
      {
        "page": "https://folk.tw/deities/miaoying_xianfei/",
        "query": "妙應仙妃由來",
        "clicks": 0,
        "impressions": 5,
        "ctr": 0,
        "position": 11.2
      },
      {
        "page": "https://folk.tw/deities/qiyebaye/",
        "query": "八爺聖誕",
        "clicks": 0,
        "impressions": 5,
        "ctr": 0,
        "position": 9.4
      },
      {
        "page": "https://folk.tw/poems/guandi_lingqian-1/",
        "query": "漢高祖入關",
        "clicks": 0,
        "impressions": 5,
        "ctr": 0,
        "position": 6.8
      },
      {
        "page": "https://folk.tw/poems/guandi_lingqian-19/",
        "query": "劉智遠得岳氏",
        "clicks": 0,
        "impressions": 5,
        "ctr": 0,
        "position": 9
      },
      {
        "page": "https://folk.tw/allusions/yangjiajiang/",
        "query": "楊文廣被困柳州城故事",
        "clicks": 0,
        "impressions": 4,
        "ctr": 0,
        "position": 7
      },
      {
        "page": "https://folk.tw/deities/guanyin/",
        "query": "觀世音 菩薩",
        "clicks": 0,
        "impressions": 4,
        "ctr": 0,
        "position": 62.75
      },
      {
        "page": "https://folk.tw/deities/wangye_fan",
        "query": "范府千歲由來",
        "clicks": 0,
        "impressions": 4,
        "ctr": 0,
        "position": 10.5
      },
      {
        "page": "https://folk.tw/poems/guandi_lingqian-24/",
        "query": "張騫誤入斗牛宮",
        "clicks": 0,
        "impressions": 4,
        "ctr": 0,
        "position": 12.5
      },
      {
        "page": "https://folk.tw/allusions/gd_27/",
        "query": "江東得道",
        "clicks": 0,
        "impressions": 3,
        "ctr": 0,
        "position": 10.333333333333334
      },
      {
        "page": "https://folk.tw/almanac/2025-08-29/",
        "query": "2025-08-29",
        "clicks": 0,
        "impressions": 3,
        "ctr": 0,
        "position": 8.666666666666668
      },
      {
        "page": "https://folk.tw/deities/chenghuang/",
        "query": "城隍",
        "clicks": 0,
        "impressions": 3,
        "ctr": 0,
        "position": 68.66666666666667
      },
      {
        "page": "https://folk.tw/deities/chenghuang/",
        "query": "城隍 爺",
        "clicks": 0,
        "impressions": 3,
        "ctr": 0,
        "position": 56
      },
      {
        "page": "https://folk.tw/deities/fazhu/",
        "query": "法 祖 公",
        "clicks": 0,
        "impressions": 3,
        "ctr": 0,
        "position": 51.333333333333336
      },
      {
        "page": "https://folk.tw/deities/kaizhang/",
        "query": "開 漳 聖王",
        "clicks": 0,
        "impressions": 3,
        "ctr": 0,
        "position": 60
      },
      {
        "page": "https://folk.tw/deities/qiyebaye/",
        "query": "七爺八爺生日",
        "clicks": 0,
        "impressions": 3,
        "ctr": 0,
        "position": 10
      },
      {
        "page": "https://folk.tw/deities/qiyebaye/",
        "query": "七爺生日",
        "clicks": 0,
        "impressions": 3,
        "ctr": 0,
        "position": 8.333333333333332
      },
      {
        "page": "https://folk.tw/poems/guandi_lingqian-63/",
        "query": "楊令公撞李陵碑",
        "clicks": 0,
        "impressions": 3,
        "ctr": 0,
        "position": 8
      },
      {
        "page": "https://folk.tw/poems/liushi_jiazi-17/",
        "query": "丙申籤",
        "clicks": 0,
        "impressions": 3,
        "ctr": 0,
        "position": 18.666666666666668
      }
    ]
  },
  "index": {
    "sitemaps": [
      {
        "path": "https://folk.tw/sitemap-0.xml",
        "submitted": 9785,
        "errors": "0",
        "warnings": "0"
      },
      {
        "path": "https://folk.tw/sitemap-index.xml",
        "submitted": 9785,
        "errors": "0",
        "warnings": "0"
      }
    ],
    "coverage": [
      {
        "url": "https://folk.tw/",
        "coverageState": "Submitted and indexed",
        "lastCrawlTime": "2026-07-01T16:04:49Z"
      },
      {
        "url": "https://folk.tw/almanac",
        "coverageState": "Page with redirect",
        "lastCrawlTime": "2026-07-01T02:03:35Z"
      },
      {
        "url": "https://folk.tw/almanac/archive",
        "coverageState": "URL is unknown to Google",
        "lastCrawlTime": null
      },
      {
        "url": "https://folk.tw/deities/mazu/",
        "coverageState": "Submitted and indexed",
        "lastCrawlTime": "2026-06-29T16:29:10Z"
      },
      {
        "url": "https://folk.tw/deities/guangong/",
        "coverageState": "URL is unknown to Google",
        "lastCrawlTime": null
      },
      {
        "url": "https://folk.tw/poems",
        "coverageState": "Crawled - currently not indexed",
        "lastCrawlTime": "2026-06-21T09:54:34Z"
      },
      {
        "url": "https://folk.tw/poems/liushi_jiazi-1/",
        "coverageState": "Submitted and indexed",
        "lastCrawlTime": "2026-06-25T09:12:39Z"
      },
      {
        "url": "https://folk.tw/allusions/suitang_qinshubao/",
        "coverageState": "Submitted and indexed",
        "lastCrawlTime": "2026-06-21T10:33:05Z"
      },
      {
        "url": "https://folk.tw/temples",
        "coverageState": "Submitted and indexed",
        "lastCrawlTime": "2026-06-21T12:18:09Z"
      },
      {
        "url": "https://folk.tw/temples/dajia_zhenlan/",
        "coverageState": "Submitted and indexed",
        "lastCrawlTime": "2026-06-21T17:05:59Z"
      },
      {
        "url": "https://folk.tw/temples/moi_0_竹圍仔福德祠/",
        "coverageState": "URL is unknown to Google",
        "lastCrawlTime": null
      }
    ]
  }
}
